spine/__init__.py
spineapi/__init__.py
spineapi-0.1.0.dist-info/LICENSE
spineapi-0.1.0.dist-info/METADATA
spineapi-0.1.0.dist-info/WHEEL
spineapi-0.1.0.dist-info/top_level.txt
spineapi-0.1.0.dist-info/RECORD
