Metadata-Version: 2.1
Name: spineapi
Version: 0.1.0
Summary: Access your python functions through HTTP requests.
Home-page: https://github.com/northfoxz/spine-api
Author: northfoxz
Author-email: firstera15@gmail.com
License: UNKNOWN
Platform: UNKNOWN
Classifier: Programming Language :: Python :: 3
Classifier: License :: OSI Approved :: MIT License
Classifier: Operating System :: OS Independent
Requires-Python: >=3.6
Requires-Dist: python-socketio[client]
